zhconv/__init__.py
zhconv/__main__.py
zhconv/zhcdict.json
zhconv/zhconv.py
zhconv-1.4.1.dist-info/LICENSE
zhconv-1.4.1.dist-info/LICENSE.data
zhconv-1.4.1.dist-info/METADATA
zhconv-1.4.1.dist-info/WHEEL
zhconv-1.4.1.dist-info/top_level.txt
zhconv-1.4.1.dist-info/RECORD
