Metadata-Version: 1.1
Name: zhconv
Version: 1.4.1
Summary: A simple implementation of Simplified-Traditional Chinese conversion.
Home-page: https://github.com/gumblex/zhconv
Author: Dingyuan Wang
Author-email: abcdoyle888@gmail.com
License: GPLv2+
Keywords: chinese conversion
Platform: any
Classifier: Development Status :: 4 - Beta
Classifier: Intended Audience :: Developers
Classifier: Topic :: Text Processing :: Linguistic
Classifier: License :: OSI Approved :: GNU General Public License v2 or later (GPLv2+)
Classifier: Natural Language :: Chinese (Simplified)
Classifier: Natural Language :: Chinese (Traditional)
Classifier: Operating System :: OS Independent
Classifier: Programming Language :: Python
Classifier: Programming Language :: Python :: 2
Classifier: Programming Language :: Python :: 3
